aioyeelight/__init__.py
aioyeelight/__main__.py
aioyeelight/aioyeelight.py
aioyeelight/discover.py
aioyeelight-0.1.0.dist-info/LICENSE.txt
aioyeelight-0.1.0.dist-info/METADATA
aioyeelight-0.1.0.dist-info/WHEEL
aioyeelight-0.1.0.dist-info/entry_points.txt
aioyeelight-0.1.0.dist-info/top_level.txt
aioyeelight-0.1.0.dist-info/RECORD
