Metadata-Version: 2.1
Name: aioyeelight
Version: 0.1.0
Summary: API for local communication with Yeelight devices over a LAN with asyncio.
Home-page: http://github.com/frawau/aioyeelight
Author: François Wautier
Author-email: francois@wautier.eu
License: MIT
Keywords: yeelight,light,automation,xiaomi
Platform: UNKNOWN
Classifier: License :: OSI Approved :: MIT License
Classifier: Programming Language :: Python :: 3
Classifier: Programming Language :: Python :: 3.5
Requires-Dist: aiozeroconf
Requires-Dist: cryptography
